scalenx/__init__.py
scalenx/scalenx.py
scalenx/scalenxsfx.py
scalenx-2025.11.15.34.dist-info/licenses/LICENSE
scalenx-2025.11.15.34.dist-info/METADATA
scalenx-2025.11.15.34.dist-info/WHEEL
scalenx-2025.11.15.34.dist-info/top_level.txt
scalenx-2025.11.15.34.dist-info/RECORD
