Metadata-Version: 2.4
Name: ScaleNx
Version: 2025.11.15.34
Summary: Image resizing using Scale2x, Scale3x, Scale2xSFX and Scale3xSFX algorithms, in pure Python.
Home-page: https://dnyarri.github.io/
Author: Ilya Razmanov
Author-email: ilyarazmanov@gmail.com
Project-URL: Source, https://github.com/Dnyarri/PixelArtScaling
Project-URL: Changelog, https://github.com/Dnyarri/PixelArtScaling/blob/py34/CHANGELOG.md
Project-URL: Issues, https://github.com/Dnyarri/PixelArtScaling/issues
Keywords: Scale2x,Scale3x,Scale2xSFX,Scale3xSFX,AdvMAME2,AdvMAME3,pixel,resize,rescale,image,bitmap,python
Classifier: Programming Language :: Python :: 3
Classifier: Programming Language :: Python :: 3.4
Classifier: Programming Language :: Python :: 3.5
Classifier: Programming Language :: Python :: 3.6
Classifier: Programming Language :: Python :: 3.7
Classifier: Programming Language :: Python :: 3.8
Classifier: Programming Language :: Python :: 3.9
Classifier: Programming Language :: Python :: 3.10
Classifier: Programming Language :: Python :: 3.11
Classifier: Programming Language :: Python :: 3.12
Classifier: Programming Language :: Python :: 3.13
Classifier: License :: OSI Approved :: The Unlicense (Unlicense)
Classifier: Operating System :: OS Independent
Classifier: Development Status :: 5 - Production/Stable
Classifier: Topic :: Multimedia :: Graphics
Classifier: Topic :: Scientific/Engineering :: Image Processing
Classifier: Topic :: Software Development :: Libraries :: Python Modules
Classifier: Intended Audience :: Developers
Classifier: Intended Audience :: Education
Classifier: Intended Audience :: Science/Research
Requires-Python: >=3.4
License-File: LICENSE
Dynamic: author
Dynamic: author-email
Dynamic: classifier
Dynamic: description
Dynamic: description-content-type
Dynamic: home-page
Dynamic: keywords
Dynamic: license-file
Dynamic: project-url
Dynamic: requires-python
Dynamic: summary
